googlegroupexporter
