Metadata-Version: 1.1
Name: googlegroupexporter
Version: 1.0
Summary: GoogleGroup Exporter - Unlock your mailing list
Home-page: https://github.com/henriquebastos/googlegroupexporter
Author: Henrique Bastos
Author-email: henrique@bastos.net
License: MIT
Keywords: googlegroup export mbox csv crawler web
Platform: UNKNOWN
Classifier: Development Status :: 4 - Beta
Classifier: Environment :: Web Environment
Classifier: License :: OSI Approved :: MIT License
Classifier: Operating System :: OS Independent
Classifier: Programming Language :: Python :: 3
Classifier: Programming Language :: Python :: 3.5
Classifier: Topic :: Internet :: WWW/HTTP
Classifier: Topic :: Utilities
